timedisagg/__init__.py
timedisagg/td.py
timedisagg-0.0.1.dist-info/LICENSE
timedisagg-0.0.1.dist-info/METADATA
timedisagg-0.0.1.dist-info/WHEEL
timedisagg-0.0.1.dist-info/top_level.txt
timedisagg-0.0.1.dist-info/RECORD
