Metadata-Version: 2.1
Name: timedisagg
Version: 0.0.1
Summary: Temporal Disaggregation of Low-Frequency Time Series Data
Home-page: https://github.com/jstephenj14/timedisagg
Author: John Selvam
Author-email: jstephenj14@gmail.com
License: UNKNOWN
Platform: UNKNOWN
Classifier: Programming Language :: Python :: 3
Classifier: License :: OSI Approved :: MIT License
Classifier: Operating System :: OS Independent
Requires-Python: >=3.6
